gpt_batch_manager/gpt_batch_manager.py
gpt_batch_manager/gpt_batch_splitter.py
gpt_batch_manager-1.0.1.dist-info/LICENSE
gpt_batch_manager-1.0.1.dist-info/METADATA
gpt_batch_manager-1.0.1.dist-info/WHEEL
gpt_batch_manager-1.0.1.dist-info/entry_points.txt
gpt_batch_manager-1.0.1.dist-info/RECORD
