Metadata-Version: 2.1
Name: gpt-batch-manager
Version: 1.0.1
Summary: Tools for splitting jobs across multiple OpenAI batches
Home-page: https://github.com/danvk/gpt-batch-manager
License: Apache-2.0
Keywords: gpt,openai,batch,splitter,api
Author: Dan Vanderkam
Author-email: danvdk@gmail.com
Requires-Python: >=3.11,<4.0
Classifier: Development Status :: 4 - Beta
Classifier: Environment :: Console
Classifier: Intended Audience :: Developers
Classifier: License :: OSI Approved :: Apache Software License
Classifier: Programming Language :: Python :: 3
Classifier: Programming Language :: Python :: 3.11
Classifier: Programming Language :: Python :: 3.12
Classifier: Topic :: Scientific/Engineering :: Artificial Intelligence
Requires-Dist: binpacking (>=1.5.2,<2.0.0)
Requires-Dist: openai (>=1.45.1,<2.0.0)
Requires-Dist: pillow (>=10.4.0,<11.0.0)
Requires-Dist: python-dotenv (>=1.0.1,<2.0.0)
Project-URL: Repository, https://github.com/danvk/gpt-batch-manager
